单周期CPU/code（实验源码）/SingleCycleCPU2.srcs/sources_1/new/ALU.v
`timescale 1ns / 1ps
//////////////////////////////////////////////////////////////////////////////////
// Company: 
// Engineer: 
// 
// Create Date: 2024/11/26 10:57:34
// Design Name: 
// Module Name: ALU
// Project Name: 
// Target Devices: 
// Tool Versions: 
// Description: 
// 
// Dependencies: 
// 
// Revision:
// Revision 0.01 - File Created
// Additional Comments:
// 
//////////////////////////////////////////////////////////////////////////////////


module ALU(
    input [31:0] ReadData1,
    input [31:0] ReadData2,
    input [31:0] immExt,
    input [4:0] shamt,
    input [2:0] ALUop,
    input ALUSrcA,ALUSrcB,
    output zero,sign,
    output reg [31:0] result
    );
    wire [31:0] InA;
    wire [31:0] InB;
    assign InA=ALUSrcA?{{27{1'b0}},shamt}:ReadData1;    //控制第一个操作数来源，0：rs寄存器；1：立即数
    assign InB=ALUSrcB?immExt:ReadData2;    //控制第二个操作数来源，0：rt寄存器；1：立即数
    assign zero=(result==0)?1:0;
    assign sign=result[31];    
    always@(*) begin
        case(ALUop)
            3'b000:
                result=InA+InB;
            3'b001:
                result=InA-InB;
            3'b010:
                result=InB<<InA;
            3'b011:
                result=InA|InB;     //或运算
            3'b100:
                result=InA&InB;
            3'b101:
                result=(InA<InB)?1:0;   //无符号数比较
            3'b110:
                result=(((InA<InB)&&(InA[31]==InB[31]))||((InA[31]==1)&&(InB[31]==0)))?1:0;     //符号数比较
            3'b111:
                result=InA^InB;     //异或运算
            default:
                result = 32'h0000;
        endcase
    end
endmodule

单周期CPU/code（实验源码）/SingleCycleCPU2.srcs/sim_1/new/ALU_sim.v
`timescale 1ns / 1ps
//////////////////////////////////////////////////////////////////////////////////
// Company: 
// Engineer: 
// 
// Create Date: 2024/11/26 12:27:12
// Design Name: 
// Module Name: ALU_sim
// Project Name: 
// Target Devices: 
// Tool Versions: 
// Description: 
// 
// Dependencies: 
// 
// Revision:
// Revision 0.01 - File Created
// Additional Comments:
// 
//////////////////////////////////////////////////////////////////////////////////


module ALU_sim();

    //input
    reg [31:0] ReadData1;
    reg [31:0] ReadData2;
    reg [31:0] immExt;
    reg [31:0] shamt;
    reg [2:0] ALUop;
    reg ALUSrcA, ALUSrcB;

    //output
    wire zero;
    wire [31:0] result;

    ALU uut(
        .ReadData1(ReadData1),
        .ReadData2(ReadData2),
        .immExt(immExt),
        .shamt(shamt),
        .ALUop(ALUop),
        .ALUSrcA(ALUSrcA),
        .ALUSrcB(ALUSrcB),
        .zero(zero),
        .result(result)
    );

    initial begin
        //record
        $dumpfile("ALU32.vcd");
        $dumpvars(0, ALU_sim);
        //add1
        ReadData1 = 0;
        ReadData2 = 0;
        immExt = 1;
        shamt = 1;
        ALUop = 3'b000;
        ALUSrcA = 0;
        ALUSrcB = 0;
        //add2
        #50;
        ReadData1 = 0;
        ReadData2 = 0;
        immExt = 1;
        shamt = 1;
        ALUop = 3'b000;
        ALUSrcA = 1;
        ALUSrcB = 0;
        //sub1
        #50;
        ReadData1 = 1;
        ReadData2 = 2;
        immExt = 3;
        shamt = 4;
        ALUop = 3'b001;
        ALUSrcA = 0;
        ALUSrcB = 0;
        //sub2
        #50;
        ReadData1 = 1;
        ReadData2 = 2;
        immExt = 3;
        shamt = 4;
        ALUop = 3'b001;
        ALUSrcA = 1;
        ALUSrcB = 0;
        //左移1
        #50;
        ReadData1 = 1;
        ReadData2 = 2;
        immExt = 2;
        shamt = 4;
        ALUop = 3'b010;
        ALUSrcA = 0;
        ALUSrcB = 0;
        //左移2
        #50;
        ReadData1 = 1;
        ReadData2 = 2;
        immExt = 2;
        shamt = 4;
        ALUop = 3'b010;
        ALUSrcA = 1;
        ALUSrcB = 0;
        //or1
        #50;
        ReadData1 = 1;
        ReadData2 = 2;
        immExt = 2;
        shamt = 4;
        ALUop = 3'b011;
        ALUSrcA = 0;
        ALUSrcB = 0;
        //or2
        #50;
        ReadData1 = 1;
        ReadData2 = 2;
        immExt = 2;
        shamt = 4;
        ALUop = 3'b011;
        ALUSrcA = 1;
        ALUSrcB = 0;
        //and1
        #50;
        ReadData1 = 1;
        ReadData2 = 2;
        immExt = 2;
        shamt = 4;
        ALUop = 3'b100;
        ALUSrcA = 0;
        ALUSrcB = 0;
        //and2
        #50;
        ReadData1 = 1;
        ReadData2 = 2;
        immExt = 2;
        shamt = 4;
        ALUop = 3'b100;
        ALUSrcA = 1;
        ALUSrcB = 0;
        //不带符号比较1
        #50;
        ReadData1 = 1;
        ReadData2 = 2;
        immExt = 2;
        shamt = 1;
        ALUop = 3'b101;
        ALUSrcA = 0;
        ALUSrcB = 0;
        //不带符号比较2
        #50;
        ReadData1 = 1;
        ReadData2 = 2;
        immExt = 2;
        shamt = 1;
        ALUop = 3'b101;
        ALUSrcA = 1;
        ALUSrcB = 0;
        //带符号比较1
        #50;
        ReadData1 = 1;
        ReadData2 = 2;
        immExt = 2;
        shamt = 1;
        ALUop = 3'b110;
        ALUSrcA = 0;
        ALUSrcB = 0;
        //带符号比较2
        #50;
        ReadData1 = 1;
        ReadData2 = 2;
        immExt = 2;
        shamt = 1;
        ALUop = 3'b110;
        ALUSrcA = 1;
        ALUSrcB = 0;
        //nor1
        #50;
        ReadData1 = 1;
        ReadData2 = 2;
        immExt = 2;
        shamt = 1;
        ALUop = 3'b111;
        ALUSrcA = 0;
        ALUSrcB = 0;
        //nor2
        #50;
        ReadData1 = 1;
        ReadData2 = 2;
        immExt = 2;
        shamt = 1;
        ALUop = 3'b111;
        ALUSrcA = 1;
        ALUSrcB = 0;
        //stop
        #50;
        $stop;
    end

endmodule

单周期CPU/code（实验源码）/SingleCycleCPU2.sim/sim_1/behav/xsim/ALU32.vcd
$date
   Wed Nov 27 17:06:09 2024
$end
$version
  2017.4
$end
$timescale
  1ps
$end
$scope module ALU_sim $end
$var reg 32 ! ReadData1 [31:0] $end
$var reg 32 " ReadData2 [31:0] $end
$var reg 32 # immExt [31:0] $end
$var reg 32 $ shamt [31:0] $end
$var reg 3 % ALUop [2:0] $end
$var reg 1 & ALUSrcA $end
$var reg 1 ' ALUSrcB $end
$var wire 1 ( zero $end
$var wire 32 ) result [31:0] $end
$scope module uut $end
$var wire 32 * ReadData1 [31:0] $end
$var wire 32 + ReadData2 [31:0] $end
$var wire 32 , immExt [31:0] $end
$var wire 5 - shamt [4:0] $end
$var wire 3 . ALUop [2:0] $end
$var wire 1 / ALUSrcA $end
$var wire 1 0 ALUSrcB $end
$var wire 1 ( zero $end
$var wire 1 1 sign $end
$var reg 32 2 result [31:0] $end
$var wire 32 3 InA [31:0] $end
$var wire 32 4 InB [31:0] $end
$upscope $end
$upscope $end
$enddefinitions $end
#0
$dumpvars
b0 !
b0 "
b1 #
b1 $
b0 %
0&
0'
1(
b0 )
b0 *
b0 +
b1 ,
b1 -
b0 .
0/
00
01
b0 2
b0 3
b0 4
$end
#50000
b0 !
b0 "
b1 #
b1 $
b0 %
1&
0(
b1 )
1/
b1 2
b1 3
#100000
b1 !
b10 "
b11 #
b100 $
b1 %
0&
b11111111111111111111111111111111 )
b1 *
b10 +
b11 ,
b100 -
b1 .
0/
11
b11111111111111111111111111111111 2
b1 3
b10 4
#150000
b1 !
b10 "
b11 #
b100 $
b1 %
1&
b10 )
1/
01
b10 2
b100 3
#200000
b1 !
b10 "
b10 #
b100 $
b10 %
0&
b100 )
b10 ,
b10 .
0/
b100 2
b1 3
b10 4
#250000
b1 !
b10 "
b10 #
b100 $
b10 %
1&
b100000 )
1/
b100000 2
b100 3
#300000
b1 !
b10 "
b10 #
b100 $
b11 %
0&
b11 )
b11 .
0/
b11 2
b1 3
#350000
b1 !
b10 "
b10 #
b100 $
b11 %
1&
b110 )
1/
b110 2
b100 3
#400000
b1 !
b10 "
b10 #
b100 $
b100 %
0&
1(
b0 )
b100 .
0/
b0 2
b1 3
#450000
b1 !
b10 "
b10 #
b100 $
b100 %
1&
1/
b0 2
b100 3
#500000
b1 !
b10 "
b10 #
b1 $
b101 %
0&
0(
b1 )
b1 -
b101 .
0/
b1 2
b1 3
#550000
b1 !
b10 "
b10 #
b1 $
b101 %
1&
1/
b1 3
#600000
b1 !
b10 "
b10 #
b1 $
b110 %
0&
b110 .
0/
b1 2
b1 3
#650000
b1 !
b10 "
b10 #
b1 $
b110 %
1&
1/
b1 3
#700000
b1 !
b10 "
b10 #
b1 $
b111 %
0&
b11 )
b111 .
0/
b11 2
b1 3
#750000
b1 !
b10 "
b10 #
b1 $
b111 %
1&
1/
b1 3
