单周期CPU/code（实验源码）/SingleCycleCPU2.srcs/sources_1/new/PC.v
`timescale 1ns / 1ps
//////////////////////////////////////////////////////////////////////////////////
// Company: 
// Engineer: 
// 
// Create Date: 2024/11/26 10:57:05
// Design Name: 
// Module Name: PC
// Project Name: 
// Target Devices: 
// Tool Versions: 
// Description: 
// 
// Dependencies: 
// 
// Revision:
// Revision 0.01 - File Created
// Additional Comments:
// 
//////////////////////////////////////////////////////////////////////////////////


module PC(
    input CLK,reset,PCWre,
    input[1:0] PCSrc,
    input [31:0] immExt,
    input [31:0] JumpPC,
    output reg [31:0] address,
    output [31:0] nextaddress,  
    output [31:0] PC4    //用于储存当前地址+4后的地址
    );
    assign PC4 = address+4;
    assign nextaddress= (PCSrc==2'b01)?address+4+(immExt<<2):((PCSrc==2'b10)?JumpPC:address + 4);//根据PCSrc的值来确定下一个指令的地址
    always @(negedge CLK) begin//当clock下降沿到来或Reset下降沿到来时，对地址进行改变或者置零
        if(reset==0) begin  //reset=0时，初始化PC为0
            address=0;
        end
        else if(PCWre) begin
            address=nextaddress;
        end
    end
endmodule

单周期CPU/code（实验源码）/SingleCycleCPU2.srcs/sim_1/new/PC_sim.v
`timescale 1ns / 1ps
//////////////////////////////////////////////////////////////////////////////////
// Company: 
// Engineer: 
// 
// Create Date: 2024/11/26 12:21:50
// Design Name: 
// Module Name: PC_sim
// Project Name: 
// Target Devices: 
// Tool Versions: 
// Description: 
// 
// Dependencies: 
// 
// Revision:
// Revision 0.01 - File Created
// Additional Comments:
// 
//////////////////////////////////////////////////////////////////////////////////


module PC_sim();
    //输入
    reg CLK;
    reg reset;
    reg PCWre;
    reg [1:0] PCSrc;
    reg [31:0] immExt;
    reg [31:0] JumpPC;
    //输出
    wire [31:0] address;
    wire [31:0] nextaddress;
    PC uut(
        .CLK(CLK),
        .reset(reset),
        .PCWre(PCWre),
        .PCSrc(PCSrc),
        .immExt(immExt),
        .nextaddress(nextaddress),
        .address(address),
        .JumpPC(JumpPC)
    );
    always #15 CLK = !CLK;  //时钟每15ns变化一次
    initial begin
        //记录数据变化
        $dumpfile("PC.vcd");
        $dumpvars(0, PC_sim);
        //初始化
        CLK = 0;
        reset = 0;
        PCWre = 0;
        PCSrc = 2'b00;
        immExt = 0;
        //不跳转，顺序执行下一条地址
        #50;
        reset = 1;
        PCWre = 1;
        PCSrc = 2'b00;
        immExt = 4;
        //不跳转，顺序执行下一条地址
        #50;
        reset = 1;
        PCWre = 1;
        PCSrc = 2'b00;
        immExt = 4;
        //偏移值跳转，执行跳转之后的指令
        #50;
        reset = 1;
        PCWre = 1;
        PCSrc = 2'b01;
        immExt = 4;
        //偏移值跳转，执行跳转之后的指令
        #50;
        reset = 1;
        PCWre = 1;
        PCSrc = 2'b01;
        immExt = 4;
        //无条件跳转，执行跳转之后的命令
        #50;
        reset = 1;
        PCWre = 1;
        PCSrc = 2'b10;
        JumpPC=8;   
        //结束
        #50;
        $stop;
    end
endmodule

单周期CPU/code（实验源码）/SingleCycleCPU2.sim/sim_1/behav/xsim/PC.vcd
$date
   Wed Nov 27 16:43:13 2024
$end
$version
  2017.4
$end
$timescale
  1ps
$end
$scope module PC_sim $end
$var reg 1 ! CLK $end
$var reg 1 " reset $end
$var reg 1 # PCWre $end
$var reg 2 $ PCSrc [1:0] $end
$var reg 32 % immExt [31:0] $end
$var reg 32 & JumpPC [31:0] $end
$var wire 32 ' address [31:0] $end
$var wire 32 ( nextaddress [31:0] $end
$scope module uut $end
$var wire 1 ) CLK $end
$var wire 1 * reset $end
$var wire 1 + PCWre $end
$var wire 2 , PCSrc [1:0] $end
$var wire 32 - immExt [31:0] $end
$var wire 32 . JumpPC [31:0] $end
$var reg 32 / address [31:0] $end
$var wire 32 ( nextaddress [31:0] $end
$var wire 32 0 PC4 [31:0] $end
$upscope $end
$upscope $end
$enddefinitions $end
#0
$dumpvars
0!
0"
0#
b0 $
b0 %
bx &
b0 '
b100 (
0)
0*
0+
b0 ,
b0 -
bx .
b0 /
b100 0
$end
#15000
1!
1)
#30000
0!
0)
b0 /
#45000
1!
1)
#50000
1"
1#
b0 $
b100 %
1*
1+
b100 -
#60000
0!
b100 '
b1000 (
0)
b100 /
b1000 0
#75000
1!
1)
#90000
0!
b1000 '
b1100 (
0)
b1000 /
b1100 0
#100000
b0 $
b100 %
#105000
1!
1)
#120000
0!
b1100 '
b10000 (
0)
b1100 /
b10000 0
#135000
1!
1)
#150000
0!
b1 $
b100 %
b100000 '
b110100 (
0)
b1 ,
b100000 /
b100100 0
#165000
1!
1)
#180000
0!
b110100 '
b1001000 (
0)
b110100 /
b111000 0
#195000
1!
1)
#200000
b1 $
b100 %
#210000
0!
b1001000 '
b1011100 (
0)
b1001000 /
b1001100 0
#225000
1!
1)
#240000
0!
b1011100 '
b1110000 (
0)
b1011100 /
b1100000 0
#250000
b10 $
b1000 &
b1000 (
b10 ,
b1000 .
#255000
1!
1)
#270000
0!
b1000 '
0)
b1000 /
b1100 0
