单周期CPU/code（实验源码）/SingleCycleCPU2.srcs/sources_1/new/SignZeroExtend.v
`timescale 1ns / 1ps
//////////////////////////////////////////////////////////////////////////////////
// Company: 
// Engineer: 
// 
// Create Date: 2024/11/26 10:59:29
// Design Name: 
// Module Name: SignZeroExtend
// Project Name: 
// Target Devices: 
// Tool Versions: 
// Description: 
// 
// Dependencies: 
// 
// Revision:
// Revision 0.01 - File Created
// Additional Comments:
// 
//////////////////////////////////////////////////////////////////////////////////


module SignZeroExtend(
    input wire [15:0] immediate,
    input ExtSel,
    output wire [31:0] immExt
    );
    assign immExt[15:0] = immediate[15:0];
    assign immExt[31:16]=(ExtSel==1)?{16{immediate[15]}}:16'b0;
    //如果ExtSel信号为1，则进行符号扩展，否则进行零扩展
endmodule

单周期CPU/code（实验源码）/SingleCycleCPU2.srcs/sources_1/new/RegisterFile.v
`timescale 1ns / 1ps
//////////////////////////////////////////////////////////////////////////////////
// Company: 
// Engineer: 
// 
// Create Date: 2024/11/26 10:58:24
// Design Name: 
// Module Name: RegisterFile
// Project Name: 
// Target Devices: 
// Tool Versions: 
// Description: 
// 
// Dependencies: 
// 
// Revision:
// Revision 0.01 - File Created
// Additional Comments:
// 
//////////////////////////////////////////////////////////////////////////////////


module RegisterFile(
    input CLK,RegDst,RegWre,DBDataSrc,
    input [4:0] rs,rt,rd,
    input [31:0] datafromALU,datafromRW,    //来自ALU计算结果的值，来自内存读取的值
    output [31:0] Data1,Data2,  //从寄存器中读取的值
    output [31:0] writeData     //写回寄存器的值
    );
    wire [4:0] writeReg;    //要写入的寄存器的端口
    assign writeReg=RegDst?rd:rt;      //控制目标地址来源，0为rt(I型指令)，1为rd(R型指令)
    assign writeData=DBDataSrc?datafromRW:datafromALU;     //控制写回寄存器的数据来源
    
    reg [31:0] register[0:31];      //定义32个32位寄存器
    integer i;
    initial begin
        for(i=0;i<32;i=i+1)
            register[i]<=0;
    end    //给每个寄存器赋初值0
    assign Data1=register[rs];
    assign Data2=register[rt];
    always @ (negedge CLK) begin
        if(RegWre)    //RegWre为1时，允许写入寄存器，并且防止寄存器0被修改(第0个寄存器恒为0)
            register[writeReg] <= writeData;    
    end
endmodule

单周期CPU/code（实验源码）/SingleCycleCPU2.srcs/sources_1/new/InstructionMemory.v
`timescale 1ns / 1ps
//////////////////////////////////////////////////////////////////////////////////
// Company: 
// Engineer: 
// 
// Create Date: 2024/11/26 10:57:58
// Design Name: 
// Module Name: InstructionMemory
// Project Name: 
// Target Devices: 
// Tool Versions: 
// Description: 
// 
// Dependencies: 
// 
// Revision:
// Revision 0.01 - File Created
// Additional Comments:
// 
//////////////////////////////////////////////////////////////////////////////////


module InstructionMemory(
    input [31:0] PC4,
    input [31:0] IAddr,
    input InsMemRW,
    output [5:0] op,
    output [4:0] rs,rt,rd,
    output signed [15:0] immediate,
    output [5:0] func,
    output[4:0] shamt,
    output [31:0] JumpPC,
    output reg [31:0] IDataOut  //输出：32位指令，用于计算JumpPC
    );
    reg [7:0] Mem[0:127];   //存储器
    assign op=IDataOut[31:26];
    assign rs=IDataOut[25:21];
    assign rt=IDataOut[20:16];
    assign rd=IDataOut[15:11];
    assign immediate=IDataOut[15:0];    
    assign func=IDataOut[5:0];
    assign shamt=IDataOut[10:6];
    assign JumpPC={{PC4[31:28]},{IDataOut[25:0]},{2'b00}};     //投机：提前计算好可能存在的跳转指令
    initial begin
        $readmemb("C:/Users/jhinx/Desktop/SingleCycleCPU2/Instructions.txt",Mem);      //从文件中读取指令     
        IDataOut=0;
    end
    always @(IAddr or InsMemRW) begin    //InsMemRW信号为1时读取存储器
        if(InsMemRW==1) begin
            IDataOut[7:0] = Mem[IAddr + 3];
            IDataOut[15:8] = Mem[IAddr + 2];
            IDataOut[23:16] = Mem[IAddr + 1];
            IDataOut[31:24] = Mem[IAddr];
        end
    end
endmodule

单周期CPU/code（实验源码）/SingleCycleCPU2.srcs/sources_1/new/DataMemory.v
`timescale 1ns / 1ps
//////////////////////////////////////////////////////////////////////////////////
// Company: 
// Engineer: 
// 
// Create Date: 2024/11/26 10:58:50
// Design Name: 
// Module Name: DataMemory
// Project Name: 
// Target Devices: 
// Tool Versions: 
// Description: 
// 
// Dependencies: 
// 
// Revision:
// Revision 0.01 - File Created
// Additional Comments:
// 
//////////////////////////////////////////////////////////////////////////////////


module DataMemory(
    input CLK,
    input wire [31:0] DAddr,
    input wire [31:0] DataIn,
    input mRD,
    input mWR,
    output wire [31:0] DMOut    //数据存储器的输出
    );
    reg [7:0] Memory [0:127];   //存储器
    wire [31:0] address;
    assign address = (DAddr<<2);      //一条指令存储在四个存储单元中
    assign DMOut[7:0]=(mRD==1)?Memory[address+3]:8'bz;//z为高阻态
    assign DMOut[15:8]=(mRD==1)?Memory[address+2]:8'bz;
    assign DMOut[23:16]=(mRD==1)?Memory[address+1]:8'bz;
    assign DMOut[31:24]=(mRD==1)?Memory[address]:8'bz;
    
    always@(negedge CLK) begin      //写操作
        if(mWR==1) begin
            Memory[address]<=DataIn[31:24];
            Memory[address+1]<=DataIn[23:16];
            Memory[address+2]<=DataIn[15:8];
            Memory[address+3]<=DataIn[7:0];
        end
    end
endmodule

单周期CPU/code（实验源码）/SingleCycleCPU2.srcs/sources_1/new/ControlUnit.v
`timescale 1ns / 1ps
//////////////////////////////////////////////////////////////////////////////////
// Company: 
// Engineer: 
// 
// Create Date: 2024/11/26 10:59:54
// Design Name: 
// Module Name: ControlUnit
// Project Name: 
// Target Devices: 
// Tool Versions: 
// Description: 
// 
// Dependencies: 
// 
// Revision:
// Revision 0.01 - File Created
// Additional Comments:
// 
//////////////////////////////////////////////////////////////////////////////////


module ControlUnit(
    input [5:0] op,
    input zero,sign,
    input [5:0] func,
    output reg PCWre,
    output reg ALUSrcA,
    output reg ALUSrcB,
    output reg DBDataSrc,
    output reg RegWre,
    output reg InsMemRW,
    output reg mRD,
    output reg mWR,
    output reg RegDst,
    output reg ExtSel,
    output reg [1:0]PCSrc,
    output reg [2:0] ALUop
);
       always@(*) begin
               case(op)
                   6'b000000: begin
                       case(func)
                           6'b100000: begin    //add
                               PCWre=1;ALUSrcA=0;ALUSrcB=0;DBDataSrc=0;RegWre=1;InsMemRW=1;mRD=0;mWR=0;RegDst=1;ExtSel=1;PCSrc=2'b00;ALUop=3'b000;
                           end
                           6'b100001: begin    //addu
                               PCWre=1;ALUSrcA=0;ALUSrcB=0;DBDataSrc=0;RegWre=1;InsMemRW=1;mRD=0;mWR=0;RegDst=1;ExtSel=1;PCSrc=2'b00;ALUop=3'b000;
                           end
                           6'b100010: begin    //sub
                               PCWre=1;ALUSrcA=0;ALUSrcB=0;DBDataSrc=0;RegWre=1;InsMemRW=1;mRD=0;mWR=0;RegDst=1;ExtSel=1;PCSrc=2'b00;ALUop=3'b001;
                           end
                           6'b100011: begin    //subu
                               PCWre=1;ALUSrcA=0;ALUSrcB=0;DBDataSrc=0;RegWre=1;InsMemRW=1;mRD=0;mWR=0;RegDst=1;ExtSel=1;PCSrc=2'b00;ALUop=3'b001;
                           end
                           6'b100100: begin    //and
                               PCWre=1;ALUSrcA=0;ALUSrcB=0;DBDataSrc=0;RegWre=1;InsMemRW=1;mRD=0;mWR=0;RegDst=1;ExtSel=1;PCSrc=2'b00;ALUop=3'b100;
                           end
                           6'b100101: begin    //or
                               PCWre=1;ALUSrcA=0;ALUSrcB=0;DBDataSrc=0;RegWre=1;InsMemRW=1;mRD=0;mWR=0;RegDst=1;ExtSel=1;PCSrc=2'b00;ALUop=3'b011;
                           end
                           6'b100110: begin    //xor
                               PCWre=1;ALUSrcA=0;ALUSrcB=0;DBDataSrc=0;RegWre=1;InsMemRW=1;mRD=0;mWR=0;RegDst=1;ExtSel=1;PCSrc=2'b00;ALUop=3'b111;
                           end
                           6'b101010: begin    //slt
                               PCWre=1;ALUSrcA=0;ALUSrcB=0;DBDataSrc=0;RegWre=1;InsMemRW=1;mRD=0;mWR=0;RegDst=1;ExtSel=1;PCSrc=2'b00;ALUop=4'b110;
                           end
                           6'b101011: begin    //sltu
                               PCWre=1;ALUSrcA=0;ALUSrcB=0;DBDataSrc=0;RegWre=1;InsMemRW=1;mRD=0;mWR=0;RegDst=1;ExtSel=1;PCSrc=2'b00;ALUop=4'b101;
                           end
                           6'b000000: begin    //sll
                               PCWre=1;ALUSrcA=1;ALUSrcB=0;DBDataSrc=0;RegWre=1;InsMemRW=1;mRD=0;mWR=0;RegDst=1;ExtSel=1;PCSrc=2'b00;ALUop=3'b010;
                           end
                          
                       endcase
                   end
                   6'b001000: begin    //addi
                       PCWre=1;ALUSrcA=0;ALUSrcB=1;DBDataSrc=0;RegWre=1;InsMemRW=1;mRD=0;mWR=0;RegDst=0;ExtSel=1;PCSrc=2'b00;ALUop=3'b000;
                   end
                   6'b001001: begin    //addiu
                       PCWre=1;ALUSrcA=0;ALUSrcB=1;DBDataSrc=0;RegWre=1;InsMemRW=1;mRD=0;mWR=0;RegDst=0;ExtSel=1;PCSrc=2'b00;ALUop=3'b000;
                   end
                   6'b001100: begin    //andi
                       PCWre=1;ALUSrcA=0;ALUSrcB=1;DBDataSrc=0;RegWre=1;InsMemRW=1;mRD=0;mWR=0;RegDst=0;ExtSel=0;PCSrc=2'b00;ALUop=3'b100;
                   end
                   6'b001101: begin    //ori
                       PCWre=1;ALUSrcA=0;ALUSrcB=1;DBDataSrc=0;RegWre=1;InsMemRW=1;mRD=0;mWR=0;RegDst=0;ExtSel=0;PCSrc=2'b00;ALUop=3'b011;
                   end
                   6'b001110: begin    //xori
                       PCWre=1;ALUSrcA=0;ALUSrcB=1;DBDataSrc=0;RegWre=1;InsMemRW=1;mRD=0;mWR=0;RegDst=0;ExtSel=0;PCSrc=2'b00;ALUop=3'b111;
                   end
                   6'b100011: begin    //lw
                       PCWre=1;ALUSrcA=0;ALUSrcB=1;DBDataSrc=1;RegWre=1;InsMemRW=1;mRD=1;mWR=0;RegDst=0;ExtSel=1;PCSrc=2'b00;ALUop=3'b000;
                   end
                   6'b101011: begin    //sw
                       PCWre=1;ALUSrcA=0;ALUSrcB=1;DBDataSrc=0;RegWre=0;InsMemRW=1;mRD=0;mWR=1;RegDst=0;ExtSel=1;PCSrc=2'b00;ALUop=3'b000;
                   end
                   6'b000100: begin    //beq
                       PCWre=1;ALUSrcA=0;ALUSrcB=0;DBDataSrc=0;RegWre=0;InsMemRW=1;mRD=0;mWR=0;RegDst=0;ExtSel=1;ALUop=3'b001;
                       PCSrc=(zero==1)?(2'b01):(2'b00);
                   end
                   6'b000101: begin    //bne
                       PCWre=1;ALUSrcA=0;ALUSrcB=0;DBDataSrc=0;RegWre=0;InsMemRW=1;mRD=0;mWR=0;RegDst=0;ExtSel=1;ALUop=3'b001;
                       PCSrc=(zero==0)?(2'b01):(2'b00);
                   end
                   6'b001010: begin    //slti
                       PCWre=1;ALUSrcA=0;ALUSrcB=1;DBDataSrc=0;RegWre=1;InsMemRW=1;mRD=0;mWR=0;RegDst=0;ExtSel=1;PCSrc=2'b00;ALUop=3'b110;
                   end
                   6'b000110: begin    //blez
                       PCWre=1;ALUSrcA=0;ALUSrcB=0;DBDataSrc=0;RegWre=0;InsMemRW=1;mRD=0;mWR=0;RegDst=0;ExtSel=1;ALUop=3'b001;
                       PCSrc=(zero==1||sign==1)?2'b01:2'b00;
                   end
                   6'b000010: begin    //j
                       PCWre=1;ALUSrcA=0;ALUSrcB=1;DBDataSrc=0;RegWre=0;InsMemRW=1;mRD=0;mWR=0;RegDst=0;ExtSel=1;PCSrc=2'b10;ALUop=3'b000;
                   end
                   6'b111111: begin    //halt
                       PCWre=0;ALUSrcA=0;ALUSrcB=1;DBDataSrc=0;RegWre=0;InsMemRW=1;mRD=0;mWR=0;RegDst=0;ExtSel=1;PCSrc=2'b00;ALUop=3'b000;
                   end
               endcase
           end
endmodule
/*   另一种实现方式
    input [5:0] op,
    input zero,sign,
    input [5:0] func,
    output PCWre,
    output ALUSrcA,
    output ALUSrcB,
    output DBDataSrc,
    output RegWre,
    output InsMemRW,
    output mRD,
    output mWR,
    output RegDst,
    output ExtSel,
    output [1:0]PCSrc,
    output [2:0] ALUop

        parameter R=6'b000000;
        assign PCWre=(op==6'b111111)?0:1;
        assign ALUSrcA=(op==R&&func==6'b000000)?1:0;
        assign ALUSrcB=(op==R||op==6'b000100||op==6'b000101||op==6'b000110)?0:1;
        assign DBDataSrc=(op==6'b100011)?1:0;
        assign RegWre=(op==6'b101011||op==6'b000100||op==6'b000101||op==6'b000110||op==6'b000010)?0:1;
        assign InsMemRW=1;
        assign mRD=(op==6'b100011)?1:0;
        assign mWR=(op==6'b101011)?1:0;
        assign RegDst=(op==R)?1:0;
        assign ExtSel=(op==R||op==6'b001100||op==6'b001101||op==6'b001110)?0:1;
        assign PCSrc=(op==6'b000010)?2'b10
                     :(op==6'b000100)?(zero==1)?2'b01:2'b00
                     :(op==6'b000101)?(zero==1)?2'b00:2'b01
                     :(op==6'b000110)?(sign==1)?2'b01:2'b00
                     :2'b00;
         assign ALUop=((op==R&&func==6'b100010)||(op==R&&func==6'b100011)||op==6'b000100||op==6'b000101||op==6'b000110)?3'b001
                     :(op==R&&func==6'b000000)?3'b010
                     :((op==R&&func==6'b100101)||op==6'b001101)?3'b011
                     :((op==R&&func==6'b100100)||op==6'b001100)?3'b100
                     :(op==R&&func==6'b101011)?3'b101
                     :((op==R&&func==6'b101010)||op==6'b001010)?3'b110
                     :((op==R&&func==6'b100110)||op==6'b001110)?3'b111
                     :3'b000;
           */

单周期CPU/code（实验源码）/SingleCycleCPU2.srcs/sources_1/new/PC.v
`timescale 1ns / 1ps
//////////////////////////////////////////////////////////////////////////////////
// Company: 
// Engineer: 
// 
// Create Date: 2024/11/26 10:57:05
// Design Name: 
// Module Name: PC
// Project Name: 
// Target Devices: 
// Tool Versions: 
// Description: 
// 
// Dependencies: 
// 
// Revision:
// Revision 0.01 - File Created
// Additional Comments:
// 
//////////////////////////////////////////////////////////////////////////////////


module PC(
    input CLK,reset,PCWre,
    input[1:0] PCSrc,
    input [31:0] immExt,
    input [31:0] JumpPC,
    output reg [31:0] address,
    output [31:0] nextaddress,  
    output [31:0] PC4    //用于储存当前地址+4后的地址
    );
    assign PC4 = address+4;
    assign nextaddress= (PCSrc==2'b01)?address+4+(immExt<<2):((PCSrc==2'b10)?JumpPC:address + 4);//根据PCSrc的值来确定下一个指令的地址
    always @(negedge CLK) begin//当clock下降沿到来或Reset下降沿到来时，对地址进行改变或者置零
        if(reset==0) begin  //reset=0时，初始化PC为0
            address=0;
        end
        else if(PCWre) begin
            address=nextaddress;
        end
    end
endmodule

单周期CPU/code（实验源码）/SingleCycleCPU2.srcs/sources_1/new/ALU.v
`timescale 1ns / 1ps
//////////////////////////////////////////////////////////////////////////////////
// Company: 
// Engineer: 
// 
// Create Date: 2024/11/26 10:57:34
// Design Name: 
// Module Name: ALU
// Project Name: 
// Target Devices: 
// Tool Versions: 
// Description: 
// 
// Dependencies: 
// 
// Revision:
// Revision 0.01 - File Created
// Additional Comments:
// 
//////////////////////////////////////////////////////////////////////////////////


module ALU(
    input [31:0] ReadData1,
    input [31:0] ReadData2,
    input [31:0] immExt,
    input [4:0] shamt,
    input [2:0] ALUop,
    input ALUSrcA,ALUSrcB,
    output zero,sign,
    output reg [31:0] result
    );
    wire [31:0] InA;
    wire [31:0] InB;
    assign InA=ALUSrcA?{{27{1'b0}},shamt}:ReadData1;    //控制第一个操作数来源，0：rs寄存器；1：立即数
    assign InB=ALUSrcB?immExt:ReadData2;    //控制第二个操作数来源，0：rt寄存器；1：立即数
    assign zero=(result==0)?1:0;
    assign sign=result[31];    
    always@(*) begin
        case(ALUop)
            3'b000:
                result=InA+InB;
            3'b001:
                result=InA-InB;
            3'b010:
                result=InB<<InA;
            3'b011:
                result=InA|InB;     //或运算
            3'b100:
                result=InA&InB;
            3'b101:
                result=(InA<InB)?1:0;   //无符号数比较
            3'b110:
                result=(((InA<InB)&&(InA[31]==InB[31]))||((InA[31]==1)&&(InB[31]==0)))?1:0;     //符号数比较
            3'b111:
                result=InA^InB;     //异或运算
            default:
                result = 32'h0000;
        endcase
    end
endmodule

单周期CPU/code（实验源码）/SingleCycleCPU2.srcs/sources_1/new/SingleCycleCPU.v
`timescale 1ns / 1ps
//////////////////////////////////////////////////////////////////////////////////
// Company: 
// Engineer: 
// 
// Create Date: 2024/11/26 11:00:29
// Design Name: 
// Module Name: SingleCycleCPU
// Project Name: 
// Target Devices: 
// Tool Versions: 
// Description: 
// 
// Dependencies: 
// 
// Revision:
// Revision 0.01 - File Created
// Additional Comments:
// 
//////////////////////////////////////////////////////////////////////////////////


module SingleCycleCPU(
    input CLK,reset,
    output wire [31:0] curPC,nextPC,IDataOut,DataOut1,DataOut2,result,writeData,
    output wire [4:0] rs,rt,rd
    );
    wire [2:0] ALUop;
    wire [31:0] immExt;
    wire [5:0] op,func;
    wire [15:0] immediate;
    wire [4:0] shamt;
    wire [31:0] JumpPC;
    wire [31:0] DMOut;
    wire [31:0] PC4;
    wire [1:0] PCSrc;
    wire zero,sign,PCWre,ALUSrcA,ALUSrcB,RegWre,InsMemRW,mRD,mWR,RegDst,DBDataSrc,ExtSel;
    
    ALU alu(DataOut1,DataOut2,immExt,shamt,ALUop,ALUSrcA,ALUSrcB,zero,sign,result);
    PC pc(CLK,reset,PCWre,PCSrc,immExt,JumpPC,curPC,nextPC,PC4);
    ControlUnit CU(op,zero,sign,func,PCWre,ALUSrcA,ALUSrcB,DBDataSrc,RegWre,InsMemRW,mRD,mWR,RegDst,ExtSel,PCSrc,ALUop);
    DataMemory DM(CLK,result,DataOut2,mRD,mWR,DMOut);
    InstructionMemory IM(PC4,curPC,InsMemRW,op,rs,rt,rd,immediate,func,shamt,JumpPC,IDataOut);
    RegisterFile RF(CLK,RegDst,RegWre,DBDataSrc,rs,rt,rd,result,DMOut,DataOut1,DataOut2,writeData);
    SignZeroExtend SZE(immediate,ExtSel,immExt);
endmodule

单周期CPU/code（实验源码）/SingleCycleCPU2.srcs/sim_1/new/SingleCycleCPU_sim.v
`timescale 1ns / 1ps
//////////////////////////////////////////////////////////////////////////////////
// Company: 
// Engineer: 
// 
// Create Date: 2024/11/26 11:01:46
// Design Name: 
// Module Name: SingleCycleCPU_sim
// Project Name: 
// Target Devices: 
// Tool Versions: 
// Description: 
// 
// Dependencies: 
// 
// Revision:
// Revision 0.01 - File Created
// Additional Comments:
// 
//////////////////////////////////////////////////////////////////////////////////


module SingleCycleCPU_sim();
    reg CLK;
    reg reset;
    //输出
    wire [31:0] curPC;
    wire [31:0] nextPC;
    wire [31:0] Instruction;
    wire [31:0] DataOut1;
    wire [31:0] DataOut2;
    wire [31:0] result;
    wire [31:0] writeData;
    wire [4:0] rs,rt,rd;
    //
    SingleCycleCPU uut(
        .CLK(CLK),
        .reset(reset),
        .curPC(curPC),
        .nextPC(nextPC),
        .IDataOut(Instruction),
        .DataOut1(DataOut1),
        .DataOut2(DataOut2),
        .result(result),
        .writeData(writeData),
        .rs(rs),
        .rt(rt),
        .rd(rd)
    );
    initial begin 
        //记录数据
        $dumpfile("SCCPU.vcd");
        $dumpvars(0, SingleCycleCPU_sim);
        //初始化输入
        CLK = 0;
        reset = 0;//刚开始设置PC为0
        #10;
        CLK = 1;
        #10;
        reset = 1;
        //产生时钟信号
        forever #20 begin
            CLK = !CLK;
        end
    end 
endmodule

单周期CPU/code（实验源码）/SingleCycleCPU2.sim/sim_1/behav/xsim/SCCPU.vcd
$date
   Mon Dec  2 17:20:18 2024
$end
$version
  2017.4
$end
$timescale
  1ps
$end
$scope module SingleCycleCPU_sim $end
$var reg 1 ! CLK $end
$var reg 1 " reset $end
$var wire 32 # curPC [31:0] $end
$var wire 32 $ nextPC [31:0] $end
$var wire 32 % Instruction [31:0] $end
$var wire 32 & DataOut1 [31:0] $end
$var wire 32 ' DataOut2 [31:0] $end
$var wire 32 ( result [31:0] $end
$var wire 32 ) writeData [31:0] $end
$var wire 5 * rs [4:0] $end
$var wire 5 + rt [4:0] $end
$var wire 5 , rd [4:0] $end
$scope module uut $end
$var wire 1 - CLK $end
$var wire 1 . reset $end
$var wire 32 # curPC [31:0] $end
$var wire 32 $ nextPC [31:0] $end
$var wire 32 % IDataOut [31:0] $end
$var wire 32 & DataOut1 [31:0] $end
$var wire 32 ' DataOut2 [31:0] $end
$var wire 32 ( result [31:0] $end
$var wire 32 ) writeData [31:0] $end
$var wire 5 * rs [4:0] $end
$var wire 5 + rt [4:0] $end
$var wire 5 , rd [4:0] $end
$var wire 3 / ALUop [2:0] $end
$var wire 32 0 immExt [31:0] $end
$var wire 6 1 op [5:0] $end
$var wire 6 2 func [5:0] $end
$var wire 16 3 immediate [15:0] $end
$var wire 5 4 shamt [4:0] $end
$var wire 32 5 JumpPC [31:0] $end
$var wire 32 6 DMOut [31:0] $end
$var wire 32 7 PC4 [31:0] $end
$var wire 2 8 PCSrc [1:0] $end
$var wire 1 9 zero $end
$var wire 1 : sign $end
$var wire 1 ; PCWre $end
$var wire 1 < ALUSrcA $end
$var wire 1 = ALUSrcB $end
$var wire 1 > RegWre $end
$var wire 1 ? InsMemRW $end
$var wire 1 @ mRD $end
$var wire 1 A mWR $end
$var wire 1 B RegDst $end
$var wire 1 C DBDataSrc $end
$var wire 1 D ExtSel $end
$scope module alu $end
$var wire 32 & ReadData1 [31:0] $end
$var wire 32 ' ReadData2 [31:0] $end
$var wire 32 0 immExt [31:0] $end
$var wire 5 4 shamt [4:0] $end
$var wire 3 / ALUop [2:0] $end
$var wire 1 < ALUSrcA $end
$var wire 1 = ALUSrcB $end
$var wire 1 9 zero $end
$var wire 1 : sign $end
$var reg 32 E result [31:0] $end
$var wire 32 F InA [31:0] $end
$var wire 32 G InB [31:0] $end
$upscope $end
$scope module pc $end
$var wire 1 - CLK $end
$var wire 1 . reset $end
$var wire 1 ; PCWre $end
$var wire 2 8 PCSrc [1:0] $end
$var wire 32 0 immExt [31:0] $end
$var wire 32 5 JumpPC [31:0] $end
$var reg 32 H address [31:0] $end
$var wire 32 $ nextaddress [31:0] $end
$var wire 32 7 PC4 [31:0] $end
$upscope $end
$scope module CU $end
$var wire 6 1 op [5:0] $end
$var wire 1 9 zero $end
$var wire 1 : sign $end
$var wire 6 2 func [5:0] $end
$var reg 1 I PCWre $end
$var reg 1 J ALUSrcA $end
$var reg 1 K ALUSrcB $end
$var reg 1 L DBDataSrc $end
$var reg 1 M RegWre $end
$var reg 1 N InsMemRW $end
$var reg 1 O mRD $end
$var reg 1 P mWR $end
$var reg 1 Q RegDst $end
$var reg 1 R ExtSel $end
$var reg 2 S PCSrc [1:0] $end
$var reg 3 T ALUop [2:0] $end
$upscope $end
$scope module DM $end
$var wire 1 - CLK $end
$var wire 32 ( DAddr [31:0] $end
$var wire 32 ' DataIn [31:0] $end
$var wire 1 @ mRD $end
$var wire 1 A mWR $end
$var wire 32 6 DMOut [31:0] $end
$var wire 32 U address [31:0] $end
$upscope $end
$scope module IM $end
$var wire 32 7 PC4 [31:0] $end
$var wire 32 # IAddr [31:0] $end
$var wire 1 ? InsMemRW $end
$var wire 6 1 op [5:0] $end
$var wire 5 * rs [4:0] $end
$var wire 5 + rt [4:0] $end
$var wire 5 , rd [4:0] $end
$var wire 16 3 immediate [15:0] $end
$var wire 6 2 func [5:0] $end
$var wire 5 4 shamt [4:0] $end
$var wire 32 5 JumpPC [31:0] $end
$var reg 32 V IDataOut [31:0] $end
$upscope $end
$scope module RF $end
$var wire 1 - CLK $end
$var wire 1 B RegDst $end
$var wire 1 > RegWre $end
$var wire 1 C DBDataSrc $end
$var wire 5 * rs [4:0] $end
$var wire 5 + rt [4:0] $end
$var wire 5 , rd [4:0] $end
$var wire 32 ( datafromALU [31:0] $end
$var wire 32 6 datafromRW [31:0] $end
$var wire 32 & Data1 [31:0] $end
$var wire 32 ' Data2 [31:0] $end
$var wire 32 ) writeData [31:0] $end
$var wire 5 W writeReg [4:0] $end
$var integer 32 X i $end
$upscope $end
$scope module SZE $end
$var wire 16 3 immediate [15:0] $end
$var wire 1 D ExtSel $end
$var wire 32 0 immExt [31:0] $end
$upscope $end
$upscope $end
$upscope $end
$enddefinitions $end
#0
$dumpvars
0!
0"
b0 #
b100 $
b100100000000010000000000001000 %
b0 &
b0 '
b1000 (
b1000 )
b0 *
b1 +
b0 ,
0-
0.
b0 /
b1000 0
b1001 1
b1000 2
b1000 3
b0 4
b1000000000000100000 5
bz 6
b100 7
b0 8
09
0:
1;
0<
1=
1>
1?
0@
0A
0B
0C
1D
b1000 E
b0 F
b1000 G
b0 H
1I
0J
1K
0L
1M
1N
0O
0P
0Q
1R
b0 S
b0 T
b100000 U
b100100000000010000000000001000 V
b1 W
b100000 X
$end
#10000
1!
1-
#20000
1"
1.
#40000
0!
b100 #
b1000 $
b110100000000100000000000000010 %
b0 &
b0 '
b10 (
b10 )
b10 +
0-
b11 /
b10 0
b1101 1
b10 2
b10 3
b10000000000000001000 5
bz 6
b1000 7
09
0D
b10 E
b10 G
b100 H
1I
0J
1K
0L
1M
1N
0O
0P
0Q
0R
b0 S
b11 T
b1000 U
b110100000000100000000000000010 V
b10 W
#60000
1!
1-
#80000
0!
b1000 #
b1100 $
b10000010001100000100000 %
b10 &
b1000 '
b1010 (
b1010 )
b10 *
b1 +
b11 ,
0-
b0 /
b1100000100000 0
b0 1
b100000 2
b1100000100000 3
b1000001000110000010000000 5
bz 6
b1100 7
09
0=
1B
1D
b1010 E
b10 F
b1000 G
b1000 H
1I
0J
0K
0L
1M
1N
0O
0P
1Q
1R
b0 S
b0 T
b101000 U
b10000010001100000100000 V
b11 W
#100000
1!
1-
#120000
0!
b1100 #
b10000 $
b11000100010100000100010 %
b1010 &
b10 '
b1000 (
b1000 )
b11 *
b10 +
b101 ,
0-
b1 /
b10100000100010 0
b100010 2
b10100000100010 3
b1100010001010000010001000 5
bz 6
b10000 7
09
0:
b1000 E
b1010 F
b10 G
b1100 H
1I
0J
0K
0L
1M
1N
0O
0P
1Q
1R
b0 S
b1 T
b100000 U
b11000100010100000100010 V
b101 W
#140000
1!
1-
#160000
0!
b10000 #
b10100 $
b101000100010000000100100 %
b1000 &
b10 '
b0 (
b0 )
b101 *
b100 ,
0-
b100 /
b10000000100100 0
b100100 2
b10000000100100 3
b10100010001000000010010000 5
bz 6
b10100 7
19
0:
b0 E
b1000 F
b10 G
b10000 H
1I
0J
0K
0L
1M
1N
0O
0P
1Q
1R
b0 S
b100 T
b0 U
b101000100010000000100100 V
b100 W
#180000
1!
1-
#200000
0!
b10100 #
b11000 $
b100000100100000000100101 %
b0 &
b10 (
b10 )
b100 *
b1000 ,
0-
b11 /
b100000000100101 0
b100101 2
b100000000100101 3
b10000010010000000010010100 5
bz 6
b11000 7
09
b10 E
b0 F
b10 G
b10100 H
1I
0J
0K
0L
1M
1N
0O
0P
1Q
1R
b0 S
b11 T
b1000 U
b100000100100000000100101 V
b1000 W
#220000
1!
1-
#240000
0!
b11000 #
b11100 $
b10000100000001000000 %
b0 &
b10 '
b100 (
b100 )
b0 *
b1000 +
0-
b10 /
b100000001000000 0
b0 2
b100000001000000 3
b1 4
b1000010000000100000000 5
bz 6
b11100 7
09
1<
b100 E
b1 F
b10 G
b11000 H
1I
1J
0K
0L
1M
1N
0O
0P
1Q
1R
b0 S
b10 T
b10000 U
b10000100000001000000 V
#260000
1!
1-
#280000
0!
b11100 #
b11000 $
b10101000000011111111111111110 %
b100 &
b1000 '
b11111111111111111111111111111100 (
b11111111111111111111111111111100 )
b1000 *
b1 +
b11111 ,
0-
b1 /
b11111111111111111111111111111110 0
b101 1
b111110 2
b1111111111111110 3
b11111 4
b100000001111111111111111000 5
bz 6
b100000 7
b1 8
09
1:
0<
0>
0B
b11111111111111111111111111111100 E
b100 F
b1000 G
b11100 H
1I
0J
0K
0L
0M
1N
0O
0P
0Q
1R
b1 S
b1 T
b11111111111111111111111111110000 U
b10101000000011111111111111110 V
b1 W
#300000
1!
1-
#320000
0!
b11000 #
b11100 $
b10000100000001000000 %
b0 &
b100 '
b1000 (
b1000 )
b0 *
b1000 +
b1000 ,
0-
b10 /
b100000001000000 0
b0 1
b0 2
b100000001000000 3
b1 4
b1000010000000100000000 5
bz 6
b11100 7
b0 8
09
0:
1<
1>
1B
b1000 E
b1 F
b100 G
b11000 H
1I
1J
0K
0L
1M
1N
0O
0P
1Q
1R
b0 S
b10 T
b100000 U
b10000100000001000000 V
b1000 W
#340000
1!
1-
#360000
0!
b11100 #
b100000 $
b10101000000011111111111111110 %
b1000 &
b1000 '
b0 (
b0 )
b1000 *
b1 +
b11111 ,
0-
b1 /
b11111111111111111111111111111110 0
b101 1
b111110 2
b1111111111111110 3
b11111 4
b100000001111111111111111000 5
bz 6
b100000 7
b0 8
19
0:
0<
0>
0B
b0 E
b1000 F
b1000 G
b11100 H
1I
0J
0K
0L
0M
1N
0O
0P
0Q
1R
b0 S
b1 T
b0 U
b10101000000011111111111111110 V
b1 W
#380000
1!
1-
#400000
0!
b100000 #
b100100 $
b101000010001100000000000000100 %
b10 &
b0 '
b1 (
b1 )
b10 *
b110 +
b0 ,
0-
b110 /
b100 0
b1010 1
b100 2
b100 3
b0 4
b1000110000000000000010000 5
bz 6
b100100 7
09
1=
1>
b1 E
b10 F
b100 G
b100000 H
1I
0J
1K
0L
1M
1N
0O
0P
0Q
1R
b0 S
b110 T
b100 U
b101000010001100000000000000100 V
b110 W
#420000
1!
1-
